{"cameraMode":{"drawMode":0,"name":"Shaded","section":"Shading Mode"},"sceneLighting":true,"audioPlay":false,"sceneViewState":{"m_AlwaysRefresh":false,"showFog":false,"showSkybox":false,"showFlares":true,"showImageEffects":true,"showParticleSystems":true,"showVisualEffectGraphs":true,"m_FxEnabled":true},"in2DMode":false,"pivot":{"x":607.0498046875,"y":-4.007123947143555,"z":-755.6385498046875},"rotation":{"x":0.008694584481418133,"y":-0.9291914701461792,"z":0.36897462606430056,"w":0.021718965843319894},"size":1.7984068393707276,"orthographic":false}