{"cameraMode":{"drawMode":0,"name":"Shaded","section":"Shading Mode"},"sceneLighting":false,"audioPlay":false,"sceneViewState":{"m_AlwaysRefresh":false,"showFog":false,"showSkybox":false,"showFlares":true,"showImageEffects":true,"showParticleSystems":true,"showVisualEffectGraphs":true,"m_FxEnabled":true},"in2DMode":false,"pivot":{"x":-1.0491201877593995,"y":0.7300758361816406,"z":2.02809476852417},"rotation":{"x":-0.1921660155057907,"y":0.036212388426065448,"z":-0.007087144535034895,"w":-0.9806791543960571},"size":3.573784351348877,"orthographic":false}